hksolvemaze/__init__.py
hksolvemaze-0.1.dist-info/License.txt
hksolvemaze-0.1.dist-info/METADATA
hksolvemaze-0.1.dist-info/WHEEL
hksolvemaze-0.1.dist-info/top_level.txt
hksolvemaze-0.1.dist-info/RECORD
