Metadata-Version: 2.1
Name: hksolvemaze
Version: 0.1
Summary: This is maze-solver code with the shortest path
Home-page: UNKNOWN
Author: Himanshu Kashyap
Author-email: UNKNOWN
License: UNKNOWN
Platform: UNKNOWN
